blockade/__init__.py
blockade/api.py
blockade/config.py
blockade/aws/__init__.py
blockade/aws/lambda-scripts/Blockade-Add-Indicators.py
blockade/aws/lambda-scripts/Blockade-Add-User.py
blockade/aws/lambda-scripts/Blockade-Get-Events.py
blockade/aws/lambda-scripts/Blockade-Get-Indicators.py
blockade/aws/lambda-scripts/Blockade-Store-Events.py
blockade/aws/lambda-scripts/__init__.py
blockade/aws/lambda-zips/Blockade-Add-Indicators.zip
blockade/aws/lambda-zips/Blockade-Add-User.zip
blockade/aws/lambda-zips/Blockade-Get-Events.zip
blockade/aws/lambda-zips/Blockade-Get-Indicators.zip
blockade/aws/lambda-zips/Blockade-Store-Events.zip
blockade/aws/lambda-zips/__init__.py
blockade/cli/__init__.py
blockade/cli/aws_serverless.py
blockade/cli/client.py
blockade/cli/config.py
blockade/common/__init__.py
blockade/common/exceptions.py
blockade/common/utils.py
blockade/libs/__init__.py
blockade/libs/events.py
blockade/libs/indicators.py
blockade_toolkit-1.1.5.dist-info/DESCRIPTION.rst
blockade_toolkit-1.1.5.dist-info/METADATA
blockade_toolkit-1.1.5.dist-info/RECORD
blockade_toolkit-1.1.5.dist-info/WHEEL
blockade_toolkit-1.1.5.dist-info/entry_points.txt
blockade_toolkit-1.1.5.dist-info/metadata.json
blockade_toolkit-1.1.5.dist-info/top_level.txt
