Metadata-Version: 2.0
Name: blockade-toolkit
Version: 1.1.5
Summary: Analyst client for administering Blockade.io
Home-page: https://github.com/blockadeio/analyst_toolbench
Author: Brandon Dixon
Author-email: info@blockade.io
License: GPLv2
Download-URL: https://github.com/blockadeio/analyst_toolbench/archive/master.zip
Keywords: threats,research,analysis,information security
Platform: UNKNOWN
Classifier: Development Status :: 4 - Beta
Classifier: Intended Audience :: Developers
Classifier: License :: OSI Approved :: GNU General Public License v2 (GPLv2)
Classifier: Natural Language :: English
Classifier: Programming Language :: Python
Classifier: Topic :: Software Development :: Libraries
Requires-Dist: boto3
Requires-Dist: ez-setup
Requires-Dist: future
Requires-Dist: grequests
Requires-Dist: requests
Requires-Dist: tldextract
